hamilton_ui/__init__.py
hamilton_ui/commands.py
hamilton_ui/manage.py
hamilton_ui/requirements-mini.txt
hamilton_ui/build/asset-manifest.json
hamilton_ui/build/favicon.png
hamilton_ui/build/index.html
hamilton_ui/build/logo.png
hamilton_ui/build/logo_with_text.svg
hamilton_ui/build/manifest.json
hamilton_ui/build/robots.txt
hamilton_ui/build/static/css/main.5f18e71d.css
hamilton_ui/build/static/css/main.5f18e71d.css.map
hamilton_ui/build/static/js/787.9e9f4ffd.chunk.js
hamilton_ui/build/static/js/787.9e9f4ffd.chunk.js.map
hamilton_ui/build/static/js/main.bcc7054c.js
hamilton_ui/build/static/js/main.bcc7054c.js.LICENSE.txt
hamilton_ui/build/static/js/main.bcc7054c.js.map
hamilton_ui/common/__init__.py
hamilton_ui/common/django_utils.py
hamilton_ui/server/__init__.py
hamilton_ui/server/api.py
hamilton_ui/server/asgi.py
hamilton_ui/server/default_views.py
hamilton_ui/server/settings.py
hamilton_ui/server/settings_mini.py
hamilton_ui/server/urls.py
hamilton_ui/server/wsgi.py
hamilton_ui/server/middleware/__init__.py
hamilton_ui/server/middleware/healthcheck.py
hamilton_ui/trackingserver_auth/__init__.py
hamilton_ui/trackingserver_auth/api.py
hamilton_ui/trackingserver_auth/apps.py
hamilton_ui/trackingserver_auth/models.py
hamilton_ui/trackingserver_auth/schema.py
hamilton_ui/trackingserver_auth/migrations/0001_initial.py
hamilton_ui/trackingserver_auth/migrations/0002_add_public_org.py
hamilton_ui/trackingserver_auth/migrations/__init__.py
hamilton_ui/trackingserver_auth/migrations_sqlite/0001_initial.py
hamilton_ui/trackingserver_auth/migrations_sqlite/0002_add_public_org.py
hamilton_ui/trackingserver_auth/migrations_sqlite/__init__.py
hamilton_ui/trackingserver_base/__init__.py
hamilton_ui/trackingserver_base/admin.py
hamilton_ui/trackingserver_base/api.py
hamilton_ui/trackingserver_base/apps.py
hamilton_ui/trackingserver_base/blob_storage.py
hamilton_ui/trackingserver_base/models.py
hamilton_ui/trackingserver_base/notifications.py
sf_hamilton_ui-0.0.17.dist-info/METADATA
sf_hamilton_ui-0.0.17.dist-info/WHEEL
sf_hamilton_ui-0.0.17.dist-info/top_level.txt
sf_hamilton_ui-0.0.17.dist-info/RECORD
