Metadata-Version: 2.4
Name: sf-hamilton-ui
Version: 0.0.17
Summary: Hamilton, the micro-framework for creating dataframes.
Home-page: https://github.com/dagworks-inc/hamilton
Author: Stefan Krawczyk, Elijah ben Izzy
Author-email: stefan@dagworks.io,elijah@dagworks.io
Project-URL: Bug Reports, https://github.com/dagworks-inc/hamilton/issues
Project-URL: Source, https://github.com/dagworks-inc/hamilton
Keywords: hamilton
Classifier: Development Status :: 5 - Production/Stable
Classifier: Intended Audience :: Developers
Classifier: Natural Language :: English
Classifier: License :: OSI Approved :: BSD License
Classifier: Programming Language :: Python :: 3
Classifier: Programming Language :: Python :: 3.8
Classifier: Programming Language :: Python :: 3.9
Classifier: Programming Language :: Python :: 3.10
Classifier: Programming Language :: Python :: 3.11
Classifier: Programming Language :: Python :: 3.12
Requires-Python: >=3.6, <4
Requires-Dist: aiofiles
Requires-Dist: psycopg2-binary
Requires-Dist: requests
Requires-Dist: typer
Requires-Dist: loguru
Requires-Dist: colorlog
Requires-Dist: aiohttp
Requires-Dist: passlib
Requires-Dist: django-ninja>=1.1.0
Requires-Dist: django
Requires-Dist: click
Requires-Dist: django-extensions
Dynamic: author
Dynamic: author-email
Dynamic: classifier
Dynamic: description
Dynamic: description-content-type
Dynamic: home-page
Dynamic: keywords
Dynamic: project-url
Dynamic: requires-dist
Dynamic: requires-python
Dynamic: summary
